markdown_field/__init__.py
markdown_field/fields.py
django_md_field-0.1.0.dist-info/METADATA
django_md_field-0.1.0.dist-info/WHEEL
django_md_field-0.1.0.dist-info/licenses/LICENSE
django_md_field-0.1.0.dist-info/RECORD
