Metadata-Version: 2.4
Name: django-md-field
Version: 0.1.0
Summary: A Django model field that integrates Python-Markdown for handling Markdown content
Project-URL: Homepage, https://github.com/jukanntenn/django-md-field
Project-URL: Issues, https://github.com/jukanntenn/django-md-field/issues
Author-email: jukanntenn <jukanntenn@outlook.com>
License: MIT
License-File: LICENSE
Keywords: django,field,markdown,model
Classifier: Development Status :: 4 - Beta
Classifier: Environment :: Web Environment
Classifier: Framework :: Django
Classifier: Framework :: Django :: 4.2
Classifier: Framework :: Django :: 5.0
Classifier: Framework :: Django :: 5.1
Classifier: Intended Audience :: Developers
Classifier: License :: OSI Approved :: MIT License
Classifier: Operating System :: OS Independent
Classifier: Programming Language :: Python
Classifier: Programming Language :: Python :: 3
Classifier: Programming Language :: Python :: 3.10
Classifier: Programming Language :: Python :: 3.11
Classifier: Programming Language :: Python :: 3.12
Classifier: Topic :: Internet :: WWW/HTTP
Requires-Python: <3.13,>=3.10
Requires-Dist: markdown<4,>=3.7
